flask_AuthGenius/__init__.py
flask_AuthGenius/auth.py
flask_AuthGenius/utils.py
flask_AuthGenius/validation.py
flask_AuthGenius/assets/Comic_Sans_MS.ttf
flask_AuthGenius/assets/Droid_Sans_Mono.ttf
flask_AuthGenius/assets/Helvetica.ttf
flask_AuthGenius/assets/languages.json
flask_AuthGenius/assets/profile_pictures.json
flask_AuthGenius/templates/login.html
flask_AuthGenius/templates/register.html
flask_AuthGenius/templates/twofactor-app.html
flask_authgenius-1.0.4.dist-info/licenses/LICENSE
flask_authgenius-1.0.4.dist-info/METADATA
flask_authgenius-1.0.4.dist-info/WHEEL
flask_authgenius-1.0.4.dist-info/top_level.txt
flask_authgenius-1.0.4.dist-info/RECORD
